tkit_mlp_pytorch/__init__.py
tkit_mlp_pytorch/mlp_pytorch.py
tkit_mlp_pytorch-0.0.0.1.dist-info/LICENSE
tkit_mlp_pytorch-0.0.0.1.dist-info/METADATA
tkit_mlp_pytorch-0.0.0.1.dist-info/WHEEL
tkit_mlp_pytorch-0.0.0.1.dist-info/top_level.txt
tkit_mlp_pytorch-0.0.0.1.dist-info/RECORD
