Metadata-Version: 2.1
Name: tkit-mlp-pytorch
Version: 0.0.0.1
Summary: Terry toolkit mlp pytorch
Home-page: https://github.com/napoler/mlp-pytorch.git
Author: Terry Chan
Author-email: napoler2008@gmail.com
License: UNKNOWN
Platform: UNKNOWN
Requires-Dist: pytorch-lightning (>=1.2.10)
